Workbook

Sheet Decision Summary
A1: DECISION SUMMARY — CY2024 MA CLASS I REC SETTLEMENT
A2: As of 2025-06-09 12:00 EDT | Contract REC-2024-017 | Prepared for Procurement and Accounting
A4: Recommended decision
A5: Decision | B5: APPROVE USD 16,920; dispute USD 1,080 of INV-2025-0617 | C5: Supported by the accepted-quantity and cover-differential bridges. | G5: Audit locator | H5: Financial Bridge!A4:F15
A6: Seller delivery accepted (RECs) | B6: ='Quantity Reconciliation'!B11 -> 950 | C6: 950 current-year Class I RECs; no duplicate serials. | G6: Audit locator | H6: Lot Dispositions!A4:U9
A7: Buyer cover admitted to inventory (RECs) | B7: ='Quantity Reconciliation'!B14 -> 40 | C7: 40; exact allocation reached BSC-MA-4421 before cutoff. | G7: Audit locator | H7: Cover Custody!A4:L4
A8: Residual shortfall (RECs) | B8: ='Quantity Reconciliation'!B15 -> 10 | C8: 10 remains open; not treated as accepted or covered. | G8: Audit locator | H8: Action Register!A5:G5
A9: Close requirement reconciliation | B9: ='Quantity Reconciliation'!B16 -> 1000 | C9: 950 seller + 40 cover + 10 residual = 1,000. | G9: Audit locator | H9: Inventory Posting!A4:F9
A11: Financial recommendation
A12: Seller invoice billed | B12: ='Financial Bridge'!D4 -> 18000 | C12: USD | D12: Invoice INV-2025-0617 p.1; Accounting/Invoice Ledger.csv row 2, fields booked_amount_usd and approval_status.
A13: Gross accepted seller value | B13: ='Financial Bridge'!D6 -> 17100 | C13: USD | D13: Contracts/REC Purchase Confirmation REC-2024-017.pdf p.1 §2; Lot Dispositions accepted quantities.
A14: Recoverable cover differential | B14: ='Financial Bridge'!D12 -> 180 | C14: USD | D14: Contracts/Amendment 1 - Cure and Cover.pdf p.3 §3; executed BRK-88402 visual pair.
A15: Prior credits | B15: ='Financial Bridge'!D13 -> 0 | C15: USD | D15: Accounting/Invoice Ledger.csv row 2, field prior_credits_usd = 0.00.
A16: Net seller payable to approve | B16: ='Financial Bridge'!D14 -> 16920 | C16: USD | D16: Financial Bridge formula: 17,100 - 180 - 0 = 16,920.
A17: Amount to dispute vs billed invoice | B17: ='Financial Bridge'!D15 -> 1080 | C17: USD | D17: Financial Bridge formula: 18,000 - 16,920 = 1,080.
A19: Authority, remedy, custody, and close controls
A20: Amendment authentication | B20: PASS — bilateral signatures dated 2025-05-20 and matching AMD-REC-017-A1 reverse received 2025-05-20 15:42 EDT. | F20: Contracts/Amendment 1 - Cure and Cover.pdf p.5 embedded signature image and p.6 embedded receipt-control reverse.
A21: Source precedence | B21: PASS — 225 CMR/DOER control eligibility; registry controls custody; authenticated Amendment 1 controls only cure, cover, and differential; base confirmation otherwise applies; EPA guide is noncontrolling. | F21: Contracts/Amendment 1 - Cure and Cover.pdf pp.1,5-6; Contracts/REC Purchase Confirmation REC-2024-017.pdf p.4 §§7-8; References/Program Authority Locator Index.md, Authority order.
A22: Cure authorization | B22: PASS — EXC-24017 notice delivered 2025-06-03 16:18; substitute delivery alone elected and received 2025-06-06 16:41; transfers completed before 17:00. Election authorized independent testing; it did not guarantee acceptance. | F22: Correspondence/Prior Exception Notice EXC-24017.pdf pp.1-2 (p.2 embedded receipt image); Correspondence/Seller Cure Election EXC-24017.docx embedded word/media/image1.jpg; Amendment p.2 §2; Registry Evidence/Account Event Export.csv rows 6-7.
A23: Cover custody | B23: PASS — BRK-88402 / ALLOC-88402-A / TX-772044, MSS424 2024Q4 004101-004140, settled to BSC-MA-4421 at 11:18:06 EDT. Inventory admission uses custody; damage uses executed fill. | F23: Registry Evidence/Cover Custody Confirmation BRK-88402.pdf pp.1-2 embedded images; Procurement/Cover Trade Capture BRK-88402.pdf p.1 embedded terminal view; Cover Custody!A4:L4.
A24: Qualification exception | B24: PASS — QX-38983-2025 for LOT-D/NON38983/MA RPS 1015-02 progressed REVIEW_HOLD → EVIDENCE_MATCHED → RELEASED at 11:36:20 EDT by Compliance Qualification Manager. Internal release gates settlement only; it does not create program eligibility. | F24: Compliance/Unit Qualification Exception Log QX-38983-2025.csv rows 4,6,8; References/RPS Class I Qualified Units.xlsx Generation Units!A18:L18.
A25: Unresolved conflict check | B25: No unresolved evidence conflict remains at cutoff. Stale 09:30 export is superseded only for LOT-C by paired live 10:03:11 reversal evidence; duplicate REPL-C serials are excluded; residual 10 remains an operational shortfall, not an evidence conflict. | F25: Registry Evidence/Account Event Export.csv row 2 metadata and row 5 LOT-C transfer; Registry Evidence/Final Lot Review Packet.pdf pp.1-2,4 embedded images; Registry Evidence/Exception Markup.docx embedded image1-image4.
A27: Required actions and separate clocks
A28: Send supported invoice dispute | B28: Procurement + Legal; Accounting records hold | D28: 2025-06-16 17:00 EDT | F28: Contracts/REC Purchase Confirmation REC-2024-017.pdf p.3 §6; Compliance/June Close Calendar.pdf p.1.
A29: Acquire/resolve residual 10 RECs and document final GIS ownership | B29: Energy Procurement + Registry Operations | D29: Before compliance inventory is finalized; monitor through filing readiness | F29: Amendment p.3 §3; References/225 CMR 14.00 Class I.pdf p.34 §14.09(2)(c).
A30: Maintain CY2024 Class I filing readiness and ownership support | B30: Compliance | D30: 2025-07-01 (authority states date; no time invented) | F30: References/225 CMR 14.00 Class I.pdf p.34 §14.09(1)-(2)(c); Compliance/June Close Calendar.pdf p.1.

Sheet Lot Dispositions
A1: LOT DISPOSITIONS
A2: Each original and replacement lot has one final lot-level disposition. Deficient quantity is tendered quantity not accepted from that row; remedy-chain consequences are stated separately.
A3: Lot | B3: Role | C3: GIS Unit | D3: MA RPS No. | E3: Qualified Unit | F3: Generation Period | G3: Serial Start | H3: Serial End | I3: Tender Qty | J3: Program Eligibility | K3: Registry Custody at Cutoff | L3: Unique Eligible Qty | M3: Internal Close Gate | N3: Final Lot Disposition | O3: Accepted Qty | P3: Deficient Qty | Q3: Remedy Path | R3: Responsible Party | S3: Timing Consequence | T3: Seller Financial Effect | U3: Precise Public Evidence
A4: LOT-A | B4: Original | C4: MSS424 | D4: 7031-24 | E4: Weldon | F4: 2024Q2 | G4: 1 | H4: 400 | I4: 400 | J4: ELIGIBLE — generation after 2024-01-01; no output limitation | K4: BUYER HELD — TX-770101 completed to BSC-MA-4421 | L4: 400 — original priority | M4: N/A | N4: ACCEPT — original lot | O4: 400 | P4: 0 | Q4: None | R4: Seller | S4: Settled before cutoff | T4: $7,200.00 | U4: Delivery/Final Delivery Statement 2025-06-09.xlsx Tender Lots!A2:I2; References/RPS Class I Qualified Units.xlsx Generation Units!A110:L110 and Notes!A5; Registry Evidence/Account Event Export.csv row 3 fields lot_id through event_status; Final Lot Review Packet.pdf p.4 embedded range matrix confirms original priority geometry.
A5: LOT-B | B5: Original | C5: NON208580 | D5: 7032-24 | E5: COVENTRY CLEAN ENERGY 1-3 | F5: 2024Q1 | G5: 1 | H5: 250 | I5: 250 | J5: INELIGIBLE — Q1 generation precedes 2024-04-01 effective date | K5: BUYER HELD in export, but custody cannot cure ineligibility | L5: 250 identity; 0 eligible | M5: N/A | N5: REJECT — pre-effective generation | O5: 0 | P5: 250 | Q5: Timely substitute REPL-B; substitute tested independently | R5: Seller | S5: Deficiency noticed; cured before 2025-06-06 17:00 EDT | T5: $0.00 | U5: Delivery statement Tender Lots!A3:I3; References/RPS Class I Qualified Units.xlsx Generation Units!A171:L171 and Notes!A5; Registry export row 4; Correspondence/Prior Exception Notice EXC-24017.pdf p.1; Amendment p.2 §2.
A6: LOT-C | B6: Original | C6: MSS424 | D6: 7031-24 | E6: Weldon | F6: 2024Q3 | G6: 1001 | H6: 1200 | I6: 200 | J6: ELIGIBLE as product/vintage | K6: REVERSED — later TX-771903 at 2025-06-09 10:03:11 EDT supersedes earlier transfer | L6: 200 identity; 0 custody-valid | M6: N/A | N6: REJECT — later reversal defeats delivery | O6: 0 | P6: 200 | Q6: Timely REPL-C; 150 unique accepted, then 40 buyer cover, 10 residual | R6: Seller (delivery deficiency); Buyer executes authorized cover | S6: Live reversal after 09:30 export but before noon cutoff | T6: $0.00 | U6: Delivery statement Tender Lots!A4:I4; Registry export row 5 (earlier transfer) and row 2 metadata; Registry Evidence/Final Lot Review Packet.pdf p.1 embedded overview and p.2 embedded detail; Registry Evidence/Exception Markup.docx embedded image1 raw and image2 marked; Amendment p.2 §2 and p.3 §3.
A7: LOT-D | B7: Original | C7: NON38983 | D7: 1015-02 | E7: Deer Island Treatment Plant STG | F7: 2024Q4 | G7: 2001 | H7: 2150 | I7: 150 | J7: ELIGIBLE — generation after 2002-04-01; no output limitation | K7: BUYER HELD — TX-770104 completed to BSC-MA-4421 | L7: 150 | M7: RELEASED — QX-38983-2025 at 11:36:20 EDT | N7: ACCEPT — valid lot after internal release gate | O7: 150 | P7: 0 | Q7: None | R7: Seller; Compliance Qualification Manager owns gate | S7: Admitted only after final pre-cutoff RELEASED event | T7: $2,700.00 | U7: Delivery statement Tender Lots!A5:I5; References/RPS Class I Qualified Units.xlsx Generation Units!A18:L18 and Notes!A5; Registry export row 6; Compliance/Unit Qualification Exception Log QX-38983-2025.csv rows 4,6,8.
A8: REPL-B | B8: Replacement for LOT-B | C8: MSS424 | D8: 7031-24 | E8: Weldon | F8: 2024Q1 | G8: 3001 | H8: 3250 | I8: 250 | J8: ELIGIBLE — Q1 generation is on/after 2024-01-01 | K8: BUYER HELD — TX-771801 completed 2025-06-06 16:48:21 EDT | L8: 250 | M8: N/A | N8: ACCEPT — substitute after independent testing | O8: 250 | P8: 0 | Q8: Cures LOT-B deficiency | R8: Seller | S8: Election 16:41 and registry transfer 16:48:21, both before 17:00 cure cutoff | T8: $4,500.00 | U8: Delivery statement Tender Lots!A6:I6; Qualified Units Generation Units!A110:L110 and Notes!A5; Registry export row 7; Prior Exception Notice pp.1-2; Seller Cure Election DOCX embedded word/media/image1.jpg; Amendment p.2 §2.
A9: REPL-C | B9: Replacement for LOT-C | C9: MSS424 | D9: 7031-24 | E9: Weldon | F9: 2024Q2 | G9: 351 | H9: 550 | I9: 200 | J9: ELIGIBLE as product/vintage | K9: BUYER HELD — TX-771802 completed 2025-06-06 16:52:08 EDT | L9: 150 — 000401-000550; 000351-000400 overlaps accepted LOT-A | M9: N/A | N9: PARTIAL ACCEPT — 150 unique; reject 50 duplicate | O9: 150 | P9: 50 | Q9: Cures 150 of LOT-C; remaining 50 proceeds to cover (40) then residual (10) | R9: Seller for duplicate deficiency; Buyer for authorized cover execution | S9: Election 16:41 and transfer 16:52:08 before cure cutoff; uniqueness then reduces acceptance | T9: $2,700.00 | U9: Delivery statement Tender Lots!A7:I7; Registry export row 8; Final Lot Review Packet.pdf p.4 embedded raw range matrix; Exception Markup.docx embedded image3 raw and image4 marked (1693×929 each); Contract p.2 §4; Amendment p.2 §2.

Sheet Quantity Reconciliation
A1: CERTIFICATE QUANTITY RECONCILIATION
A2: Inclusive serial arithmetic; original-lot priority; ordered original test → seller cure → buyer cover → residual.
A3: Step | B3: Quantity | C3: Formula / Arithmetic | D3: Treatment | E3: Owner | F3: Status | G3: Evidence / Locator
A4: Contract quantity | B4: 1000 | C4: Per confirmation | D4: Required 2024 MA Class I RECs | E4: Seller | F4: Control | G4: Contracts/REC Purchase Confirmation REC-2024-017.pdf p.1 §2.
A5: Original tender quantity | B5: =SUM('Lot Dispositions'!I4:I7) -> 1000 | C5: 400+250+200+150 | D5: All original lots tendered; not all accepted | E5: Seller | F5: Reconciled | G5: Delivery/Final Delivery Statement 2025-06-09.xlsx Tender Lots!A2:I5.
A6: Original accepted | B6: ='Lot Dispositions'!O4+'Lot Dispositions'!O7 -> 550 | C6: LOT-A 400 + LOT-D 150 | D6: Program, custody, uniqueness, and gate passed | E6: Seller | F6: 550 accepted | G6: Lot Dispositions!O4 and O7.
A7: Original deficiency before cure | B7: =B4-B6 -> 450 | C7: 1,000 - 550 | D7: LOT-B 250 + LOT-C 200 | E7: Seller | F7: 450 deficient | G7: Lot Dispositions!P5:P6.
A8: Replacement tender quantity | B8: =SUM('Lot Dispositions'!I8:I9) -> 450 | C8: 250+200 | D8: Timely cure tender; still independently tested | E8: Seller | F8: 450 tested | G8: Registry export rows 7-8; Amendment p.2 §2.
A9: Replacement accepted unique | B9: =SUM('Lot Dispositions'!O8:O9) -> 400 | C9: 250+150 | D9: REPL-B 250 + REPL-C 150 unique | E9: Seller | F9: 400 accepted | G9: Lot Dispositions!O8:O9; visual overlap pair.
A10: Replacement duplicate rejected | B10: ='Lot Dispositions'!P9 -> 50 | C10: Inclusive intersection 000351-000400 = 400-351+1 = 50 | D10: Original LOT-A priority; no double count | E10: Seller | F10: 50 rejected | G10: Final Lot Review Packet.pdf p.4 embedded range matrix; Exception Markup.docx image3 raw/image4 marked.
A11: Accepted seller total | B11: =B6+B9 -> 950 | C11: 550+400 | D11: All accepted seller components | E11: Seller | F11: 950 | G11: LOT-A 400 + LOT-D 150 + REPL-B 250 + unique REPL-C 150.
A12: Post-cure seller deficiency | B12: =B4-B11 -> 50 | C12: 1,000-950 | D12: Remaining after timely seller substitutions | E12: Seller | F12: 50 | G12: Amendment p.3 §3; Lot Dispositions.
A13: Executed cover quantity (damage basis) | B13: 40 | C13: Corroborated executed fill; does not itself prove custody | D13: Buyer / seller differential under amendment | E13: Executed | F13: 40 | G13: Cover Trade Capture p.1 embedded terminal; Broker Confirmation embedded image1.
A14: Cover admitted to inventory (custody basis) | B14: 40 | C14: Exact batch finally settled to buyer | D14: Separate inventory lineage | E14: Buyer / Registry Ops | F14: 40 posted | G14: Cover Custody Confirmation pp.1-2 embedded images; Cover Custody!A4:L4.
A15: Residual shortfall | B15: =B12-B14 -> 10 | C15: 50-40 | D15: Not accepted, not covered, not posted | E15: Energy Procurement | F15: 10 open | G15: Amendment p.3 §3; Action Register!A5:G5.
A16: Conservation check | B16: =B11+B14+B15 -> 1000 | C16: 950+40+10 | D16: Must equal contract / close requirement | E16: Settlement Management | F16: PASS if 1,000 | G16: Inventory Posting!A4:F9.

Sheet Financial Bridge
A1: FINANCIAL BRIDGE — INV-2025-0617
A2: Only accepted seller RECs are valued at USD 18.00; cover cash cost is shown separately; only the positive cover-price differential is a seller offset.
A3: Line | B3: Quantity | C3: Unit Price / Rate | D3: Amount (USD) | E3: Accounting Treatment | F3: Evidence / Locator
A4: Seller invoice billed | B4: 1000 | C4: 18 | D4: =B4*C4 -> 18000 | E4: Booked USD 18,000; unapproved; zero paid | F4: Delivery/Invoice INV-2025-0617.pdf p.1; Accounting/Invoice Ledger.csv row 2.
A5: Less: rejected seller quantity | B5: ='Quantity Reconciliation'!B12 -> 50 | C5: 18 | D5: =B5*C5 -> 900 | E5: 50 post-cure deficiency is not payable | F5: Quantity Reconciliation!B12; Contract p.2 §4 and p.3 §5.
A6: Gross accepted seller value | B6: ='Quantity Reconciliation'!B11 -> 950 | C6: 18 | D6: =B6*C6 -> 17100 | E6: 950 accepted seller RECs × contract price | F6: Contract p.1 §2; Lot Dispositions accepted vector.
A7: Executed cover price (separate trade) | B7: 40 | C7: 22.5 | D7: =B7*C7 -> 900 | E7: USD 900 buyer cover cash cost; not seller contract price and not itself a seller credit | F7: Cover Trade Capture p.1 embedded terminal; Broker Confirmation DOCX embedded image1; Cover Payment Advice p.1.
A8: Contract benchmark for covered quantity | B8: 40 | C8: 18 | D8: =B8*C8 -> 720 | E8: USD 720 contract-price baseline used only in differential | F8: Contract p.1 §2; Amendment p.3 §3.
A9: Positive unit differential | B9: 1 | C9: =MAX(C7-C8,0) -> 4.5 | D9: =C9 -> 4.5 | E9: 22.50 - 18.00 = 4.50 per covered REC | F9: Amendment p.3 §3.
A10: Eligible covered quantity | B10: 40 | C10: =C9 -> 4.5 | D10: =B10*C10 -> 180 | E10: Limited to post-cure deficiency and corroborated executed fill | F10: Amendment p.3 §3; cover visual pair.
A11: Cover cost (memo only) | B11: 40 | C11: 22.5 | D11: =B11*C11 -> 900 | E11: Buyer cash cost shown separately; do not deduct USD 900 from seller invoice | F11: Procurement/Cover Payment Advice.pdf p.1 says not a seller credit memo.
A12: Recoverable cover differential | B12: 40 | C12: =C9 -> 4.5 | D12: =B12*C12 -> 180 | E12: Permitted seller offset: 40 × 4.50 | F12: Amendment p.3 §3.
A13: Prior supported credits | B13: 1 | C13: 0 | D13: =B13*C13 -> 0 | E13: None as of cutoff | F13: Accounting/Invoice Ledger.csv row 2, prior_credits_usd = 0.00.
A14: Net seller payable to approve | D14: =D6-D12-D13 -> 16920 | E14: 17,100 - 180 - 0 = 16,920 | F14: Contract, amendment, lot and ledger evidence above.
A15: Amount to dispute vs invoice | D15: =D4-D14 -> 1080 | E15: 18,000 - 16,920 = 1,080 (USD 900 quantity rejection + USD 180 cover differential) | F15: Invoice p.1; June Close Calendar p.1; Contract p.3 §6.

Sheet Contract Cure Controls
A1: CONTRACT, AUTHENTICATION, CURE, AND COVER CONTROLS
A2: Commercial terms are applied only within their authenticated and expressly modified scope.
A3: Control | B3: Observed Identity | C3: Observed Time / Status | D3: Cutoff / Requirement | E3: Conclusion | F3: Business Consequence | G3: Primary Public Evidence | H3: Corroborating Evidence
A4: Amendment signature page | B4: AMD-REC-017-A1; Bay State / Michael T. Burns and GreenArc / Zachary Green signatures; both dated May 20, 2025; buyer/seller initials for §3 | C4: Bilateral execution visible | D4: Before noon cutoff | E4: Authenticated member 1 of 2 | F4: Supplies bilateral execution; not receipt control alone | G4: Contracts/Amendment 1 - Cure and Cover.pdf p.5 embedded signature image | H4: Same PDF p.1 document control code and p.6 reverse.
A5: Amendment receipt reverse | B5: AMD-REC-017-A1; “2 OF 2” | C5: RECEIVED MAY 20 2025 3:42 PM EDT | D5: Before noon cutoff | E5: Authenticated member 2 of 2 | F5: Matching control identity + receipt completes execution authentication | G5: Contracts/Amendment 1 - Cure and Cover.pdf p.6 embedded receipt-control reverse | H5: Same PDF p.5 signature image.
A6: Amendment precedence | B6: AMD-REC-017-A1 / REC-2024-017 | C6: Fully executed | D6: Expressly modifies exception cure, buyer cover, and damages only | E6: PASS | F6: Amendment controls those inconsistent terms; program eligibility and registry custody remain with their own authorities | G6: Amendment p.1 §1 and pp.5-6 embedded execution images | H6: Base Confirmation p.4 §§7-8; Program Authority Locator Index.md Authority order.
A7: Exception notice receipt | B7: EXC-24017; LOT-B and LOT-C | C7: DELIVERED JUN 3 2025 4:18 PM EDT | D7: Antecedent notice | E7: PASS | F7: Starts case-linked cure sequence; notice itself makes no lot disposition | G7: Prior Exception Notice EXC-24017.pdf p.1 and p.2 embedded receipt image | H7: Seller Cure Election DOCX embedded scan.
A8: Seller cure election | B8: EXC-24017; SUBSTITUTE DELIVERY is sole checked option; signed Daniel Harper | C8: RECEIVED JUN 6 2025 4:41 PM EDT | D8: No later than Jun 6 17:00 EDT | E8: TIMELY | F8: Authorizes substitute testing; does not guarantee acceptance | G8: Correspondence/Seller Cure Election EXC-24017.docx embedded word/media/image1.jpg | H8: Amendment p.2 §2; notice pp.1-2.
A9: Substitute transfers | B9: REPL-B TX-771801; REPL-C TX-771802 | C9: 16:48:21 and 16:52:08 EDT on Jun 6; completed to BSC-MA-4421 | D9: No later than Jun 6 17:00 EDT | E9: TIMELY | F9: Both substitutes enter independent product/vintage/qualification/custody/uniqueness testing | G9: Registry Evidence/Account Event Export.csv rows 7-8 | H9: Amendment p.2 §2; delivery statement Tender Lots rows 6-7.
A10: Executed cover fill | B10: BRK-88402; MAI24 / 2024 MA CLASS I; 40; USD 22.50; FILLED/EXECUTED | C10: 2025-06-09 10:47:26 EDT | D10: After Jun 6 17:00 cure expiry and before Jun 9 noon | E10: ELIGIBLE EXECUTED COVER | F10: Supports damage quantity and USD 4.50 differential; custody separately tested | G10: Procurement/Cover Trade Capture BRK-88402.pdf p.1 embedded terminal view | H10: Procurement/Broker Confirmation BRK-88402.docx embedded word/media/image1.jpg.
A11: Payment linkage | B11: PAY-2025-0609-88402 to BRK-88402; USD 900 | C11: Released for broker settlement | D11: Memo only | E11: LINKED, NOT SELLER CREDIT | F11: Confirms broker cash settlement; does not prove quantity/price and is not a seller credit memo | G11: Procurement/Cover Payment Advice.pdf p.1 | H11: Executed cover pair above.

Sheet Registry Lineage
A1: REGISTRY LIFECYCLE AND RAW-TO-MARKED LINEAGE
A2: Visual observations are admitted only after the exact raw view and dimension-preserved attention layer are reconciled.
A3: Control / Pair | B3: Public Container + Locator | C3: Dimensions | D3: Lot / Unit / Period | E3: Transaction / Range | F3: Observed Event / Geometry | G3: Time / Status | H3: Raw-to-Marked Preservation | I3: Admissible Business Conclusion | J3: Corroborating Locator
A4: LOT-C overview | B4: Registry Evidence/Final Lot Review Packet.pdf p.1 embedded overview image | C4: 1693×929 | D4: LOT-C / MSS424 / 2024Q3 | E4: Transfer TX-770512; reversal TX-771903 | F4: Ordered transfer then reversal for quantity 200 | G4: Transfer 2025-06-01 09:15:42 COMPLETED; reversal 2025-06-09 10:03:11 REVERSED | H4: Raw overview; sequence view | I4: Later adverse lifecycle event exists for same LOT-C | J4: Packet p.2 embedded detail image.
A5: LOT-C detail | B5: Registry Evidence/Final Lot Review Packet.pdf p.2 embedded detail image | C5: 1536×1024 | D5: LOT-C / MSS424 / 2024Q3 | E5: TX-771903 / 001001-001200 inclusive | F5: Buyer BSC-MA-4421; adverse status REVERSED | G5: 2025-06-09 10:03:11 EDT | H5: Raw baseline identity and scope | I5: Exact full LOT-C block reversed before cutoff | J5: Packet p.1 embedded overview; export row 5 earlier transfer.
A6: LOT-C raw lineage | B6: Registry Evidence/Exception Markup.docx embedded word/media/image1.png | C6: 1536×1024 | D6: LOT-C / MSS424 / 2024Q3 | E6: TX-771903 / 001001-001200 | F6: Unannotated retained source | G6: REVERSED at 10:03:11 EDT | H6: Exact extracted baseline from Packet p.2; unchanged dimensions | I6: Raw source is the evidentiary baseline | J6: Final Lot Review Packet.pdf p.2 embedded detail.
A7: LOT-C marked lineage | B7: Registry Evidence/Exception Markup.docx embedded word/media/image2.png | C7: 1536×1024 | D7: Same as immediately preceding raw | E7: Same TX-771903 and full range | F7: Only orange arrow/boxes added around transaction, REVERSED, and event time | G7: Source values unchanged | H7: Same dimensions and source content; bounded attention only | I7: Admitted only together with raw; annotation does not replace evidence | J7: Exception Markup DOCX paras “Source view” and “Analyst attention layer”.
A8: Overlap raw baseline | B8: Registry Evidence/Exception Markup.docx embedded word/media/image3.png | C8: 1693×929 | D8: LOT-A and REPL-C / MSS424 / 2024Q2 | E8: LOT-A 000001-000400; REPL-C 000351-000550 | F8: Shared geometry 000351-000400 | G8: Inclusive interval | H8: Exact extracted baseline from Packet p.4; unchanged dimensions | I8: Original and replacement ranges intersect | J8: Final Lot Review Packet.pdf p.4 embedded range matrix.
A9: Overlap marked lineage | B9: Registry Evidence/Exception Markup.docx embedded word/media/image4.png | C9: 1693×929 | D9: Same unit and period | E9: Same endpoints | F9: Only bounded bracket added over 000351-000400; source endpoints/bars unchanged | G9: Inclusive overlap = 400-351+1 = 50 | H9: Same dimensions and unchanged source content | I9: Original-lot priority retains only REPL-C 000401-000550 = 150 unique | J9: Contract p.2 §4 duplicate rejection; Lot Dispositions REPL-C row.
A10: Export staleness boundary | B10: Registry Evidence/Account Event Export.csv row 2 metadata and row 5 LOT-C | C10: Structured | D10: LOT-C / MSS424 / 2024Q3 | E10: Earlier TX-770512 transfer | F10: Scheduled extract ends before live reversal | G10: Cutoff 09:30; live reversal 10:03:11 | H10: No conflict: different evidence cutoffs | I10: Use live later reversal; do not use missing export event as proof of custody | J10: Final Lot Review Packet pp.1-2.

Sheet Eligibility
A1: PROGRAM ELIGIBILITY, VINTAGE, AND CUSTODY TESTS
A2: Generation period determines vintage. DOER unit data controls qualification; registry controls custody; internal exception release is a separate settlement gate.
A3: Lot | B3: GIS Unit | C3: MA RPS | D3: Unit Name | E3: Technology | F3: Generation Period | G3: RPS Effective Date | H3: Output Limitation | I3: 2024 Vintage? | J3: Qualification Result | K3: Custody / Uniqueness Result | L3: Precise Public Evidence
A4: LOT-A | B4: MSS424 | C4: 7031-24 | D4: Weldon | E4: Hydroelectric | F4: 2024Q2 | G4: 2024-01-01 | H4: Blank = no limitation | I4: YES | J4: ELIGIBLE | K4: Buyer held; original priority; 400 unique | L4: Qualified Units Generation Units!A110:L110; Notes!A5; Delivery statement Tender Lots!A2:I2; export row 3; Final Lot Review Packet p.4.
A5: LOT-B | B5: NON208580 | C5: 7032-24 | D5: COVENTRY CLEAN ENERGY 1-3 | E5: Landfill Gas | F5: 2024Q1 | G5: 2024-04-01 | H5: Blank = no limitation | I5: YES | J5: INELIGIBLE — generation precedes effective date | K5: Buyer custody does not cure program failure | L5: Qualified Units Generation Units!A171:L171; Notes!A5; Delivery statement Tender Lots!A3:I3; export row 4.
A6: LOT-C | B6: MSS424 | C6: 7031-24 | D6: Weldon | E6: Hydroelectric | F6: 2024Q3 | G6: 2024-01-01 | H6: Blank = no limitation | I6: YES | J6: ELIGIBLE product/vintage | K6: REJECT — later reversal defeats custody | L6: Qualified Units Generation Units!A110:L110; Delivery statement Tender Lots!A4:I4; Final Lot Review Packet pp.1-2 embedded images.
A7: LOT-D | B7: NON38983 | C7: 1015-02 | D7: Deer Island Treatment Plant STG | E7: Anaerobic Digester | F7: 2024Q4 | G7: 2002-04-01 | H7: Blank = no limitation | I7: YES | J7: ELIGIBLE | K7: Buyer held; 150 unique; internal case separately RELEASED | L7: Qualified Units Generation Units!A18:L18; Notes!A5; Delivery statement Tender Lots!A5:I5; export row 6; qualification log rows 4,6,8.
A8: REPL-B | B8: MSS424 | C8: 7031-24 | D8: Weldon | E8: Hydroelectric | F8: 2024Q1 | G8: 2024-01-01 | H8: Blank = no limitation | I8: YES | J8: ELIGIBLE | K8: Buyer held; 250 unique | L8: Qualified Units Generation Units!A110:L110; Delivery statement Tender Lots!A6:I6; export row 7.
A9: REPL-C | B9: MSS424 | C9: 7031-24 | D9: Weldon | E9: Hydroelectric | F9: 2024Q2 | G9: 2024-01-01 | H9: Blank = no limitation | I9: YES | J9: ELIGIBLE | K9: Buyer held; only 150 unique after 50 overlap | L9: Qualified Units Generation Units!A110:L110; Delivery statement Tender Lots!A7:I7; export row 8; raw/marked overlap pair.
A10: COVER | B10: MSS424 | C10: 7031-24 | D10: Weldon | E10: Hydroelectric | F10: 2024Q4 | G10: 2024-01-01 | H10: Blank = no limitation | I10: YES | J10: ELIGIBLE | K10: BSC-MA-4421 final owner; 40 unique allocated certificates | L10: Cover Custody Confirmation pp.1-2 embedded images; Qualified Units Generation Units!A110:L110; 225 CMR p.34 §14.09(2)(c).

Sheet Cover Custody
A1: COVER TRADE → ALLOCATION → FINAL REGISTRY CUSTODY
A2: Executed-trade damages and compliance-inventory custody are distinct tests. The current state passes both, but for different evidence reasons.
A3: Trade ID | B3: Allocation ID | C3: Program / RPS | D3: GIS Unit | E3: Generation Period | F3: Serial Start | G3: Serial End | H3: Quantity | I3: Buyer Account | J3: Registry Transaction | K3: Final Status / Time | L3: Conclusion + Precise Public Evidence
A4: BRK-88402 | B4: ALLOC-88402-A | C4: MA RPS 7031-24 | D4: MSS424 | E4: 2024Q4 | F4: 4101 | G4: 4140 | H4: =G4-F4+1 -> 40 | I4: BSC-MA-4421 | J4: TX-772044 | K4: SETTLED — 2025-06-09 11:18:06 EDT | L4: EXACT MATCH / PASS. Allocation image: Registry Evidence/Cover Custody Confirmation BRK-88402.pdf p.1 embedded ticket (trade, allocation, program, unit, buyer, period, inclusive serials, released 11:06:14). Registry image: same PDF p.2 embedded receipt (allocation, TX-772044, BSC-MA-4421 current owner, same program/unit/period/serials, SETTLED 11:18:06). Both before noon.
A6: Separate consequences
A7: Executed-trade damage test | B7: BRK-88402 executed for 40 at USD 22.50 at 10:47:26 after cure expiry and before cutoff. | E7: Supports 40 × max(22.50 − 18.00,0) = USD 180 seller offset even though trade execution alone does not prove inventory custody. | I7: Procurement/Cover Trade Capture BRK-88402.pdf p.1 embedded terminal; Broker Confirmation BRK-88402.docx embedded image1; Amendment p.3 §3.
A8: Compliance-inventory custody test | B8: Exact ALLOC-88402-A batch reached BSC-MA-4421 in final SETTLED state at 11:18:06. | E8: Supports separate 40-REC inventory posting. If final receipt were pending/reversed/late/wrong account, inventory posting would be zero while executed-trade damage conclusion remained analytically separate. | I8: Registry Evidence/Cover Custody Confirmation BRK-88402.pdf pp.1-2 embedded images; 225 CMR 14.00 p.34 §14.09(2)(c).

Sheet Qualification Exception
A1: LOT-D QUALIFICATION-EXCEPTION STATE GATE
A2: Case QX-38983-2025 is an internal settlement close control. Official DOER unit qualification is tested first and independently.
A3: Event Order | B3: Event ID | C3: Case ID | D3: Lot | E3: GIS Unit | F3: MA RPS | G3: Unit Name | H3: Status | I3: Effective At / Owner | J3: Precise Public Evidence
A4: 1 | B4: QX38983-001 | C4: QX-38983-2025 | D4: LOT-D | E4: NON38983 | F4: 1015-02 | G4: Deer Island Treatment Plant STG | H4: REVIEW_HOLD | I4: 2025-06-09 09:42:15 EDT | Compliance Qualification Desk | J4: Compliance/Unit Qualification Exception Log QX-38983-2025.csv row 4, all fields.
A5: 2 | B5: QX38983-002 | C5: QX-38983-2025 | D5: LOT-D | E5: NON38983 | F5: 1015-02 | G5: Deer Island Treatment Plant STG | H5: EVIDENCE_MATCHED | I5: 2025-06-09 11:19:44 EDT | Compliance Qualification Desk | J5: Same CSV row 6, all fields.
A6: 3 | B6: QX38983-003 | C6: QX-38983-2025 | D6: LOT-D | E6: NON38983 | F6: 1015-02 | G6: Deer Island Treatment Plant STG | H6: RELEASED | I6: 2025-06-09 11:36:20 EDT | Compliance Qualification Manager | J6: Same CSV row 8, all fields.
A8: Derived control conclusion
A9: Official program eligibility | B9: NON38983 / MA RPS 1015-02 / Deer Island / Anaerobic Digester / effective 2002-04-01; 2024Q4 generation passes. | G9: References/RPS Class I Qualified Units.xlsx Generation Units!A18:L18 and Notes!A5. This authority controls eligibility.
A10: Internal settlement gate | B10: Last exact-case event effective by noon is RELEASED at 11:36:20 EDT by Compliance Qualification Manager. Gate = PASS. | G10: Qualification log rows 4,6,8. The release permits the otherwise valid 150 LOT-D RECs to propagate to acceptance, payable, and inventory.
A11: Authority boundary | B11: The internal release does not create or override program eligibility; a DOER-invalid unit would remain ineligible even if internally released. | G11: 225 CMR 14.00 p.9 §14.05; Qualified Units row 18; Qualification log.
A12: Current propagation | B12: LOT-D accepted 150; seller accepted remains 950; gross USD 17,100; net USD 16,920; seller inventory 950. | G12: Lot Dispositions!A7:U7; Quantity Reconciliation!B11; Financial Bridge!D6,D14; Inventory Posting!B6.
A13: Control counterfactual (not current state) | B13: If RELEASED were absent, late, or mismatched, LOT-D would remain outside close: seller accepted 800; residual 160 after same 40 cover; gross USD 14,400; net USD 14,220. | G13: This is a sensitivity control illustrating the gate; it is not the current conclusion.

Sheet Inventory Posting
A1: COMPLIANCE INVENTORY POSTING VECTOR
A2: Seller and cover certificates retain separate lineage; unresolved residual remains outside settled inventory.
A3: Posting Component | B3: Quantity | C3: Class / Vintage | D3: Registry / Trade Lineage | E3: Treatment | F3: Evidence / Locator
A4: CY2024 Class I close requirement | B4: 1000 | C4: CY2024 MA RPS Class I | D4: Planning control | E4: Requirement | F4: Compliance/2024 Class I Inventory Control.xlsx Close Control!A2:E2.
A5: Opening eligible inventory | B5: 0 | C5: CY2024 allocation | D5: Pre-contract inventory | E5: Recorded | F5: Inventory Control Close Control!A3:E3.
A6: Accepted seller certificates | B6: ='Quantity Reconciliation'!B11 -> 950 | C6: 2024 Class I | D6: LOT-A 400 + LOT-D 150 + REPL-B 250 + REPL-C unique 150 | E6: POST 950 separately | F6: Official interface: References/2024 Annual Compliance Workbook.xlsx 5. RPS I non-SCO!F13; Lot Dispositions.
A7: Buyer cover certificates | B7: ='Quantity Reconciliation'!B14 -> 40 | C7: 2024 Class I | D7: BRK-88402 / ALLOC-88402-A / TX-772044 | E7: POST 40 separately after final custody | F7: Cover Custody Confirmation pp.1-2 embedded images; Cover Custody!A4:L4.
A8: Rejected / duplicate certificates | B8: 500 | C8: Excluded source records | D8: LOT-B 250 + LOT-C 200 + duplicate REPL-C 50 | E8: DO NOT POST; replacement/cover effects appear only in their own lines | F8: Lot Dispositions deficient fields and reasons; Annual Compliance Workbook 4. Errant!B9,B13 provides unsettled/status interface.
A9: Residual unresolved close balance | B9: =B4-B6-B7 -> 10 | C9: 2024 Class I needed | D9: No certificate identity yet | E9: KEEP OUTSIDE SETTLED INVENTORY; open follow-up | F9: Amendment p.3 §3; Action Register!A5:G5.
A10: Reconciliation | B10: =B6+B7+B9 -> 1000 | D10: 950 seller + 40 cover + 10 residual | E10: PASS = 1,000 | F10: 225 CMR 14.00 p.34 §14.09(2)(c) requires ownership support.

Sheet Action Register
A1: NOTICE, FOLLOW-UP, AND DEADLINE REGISTER
A2: Commercial dispute and regulatory filing are separate clocks. No filing time is invented.
A3: Action | B3: Owner | C3: Trigger / Scope | D3: Governing Deadline | E3: Status at Cutoff | F3: Required Output | G3: Precise Public Evidence
A4: Send supported dispute for USD 1,080 | B4: Procurement + Legal; Accounting records invoice hold | C4: Final tender received 2025-06-09 09:15 EDT; fifth Business Day starts next day | D4: 2025-06-16 17:00 EDT | E4: OPEN | F4: Written dispute identifies 50 post-cure deficient RECs and USD 180 cover differential; approve balance USD 16,920 | G4: Contract p.3 §6; Delivery statement Tender Lots!H2:H7; June Close Calendar p.1; Financial Bridge!D14:D15.
A5: Acquire or otherwise resolve residual 10 Class I RECs | B5: Energy Procurement | C5: After timely cure exhausted and 40 eligible cover admitted | D5: Before compliance inventory is finalized; monitor through filing readiness | E5: OPEN — 10 | F5: New certificate identity plus final GIS ownership evidence; do not post until custody verified | G5: Amendment p.3 §3; Cover Custody!A4:L4; Quantity Reconciliation!B15.
A6: Preserve raw/marked evidence lineage | B6: Registry Operations | C6: LOT-C reversal and LOT-A/REPL-C overlap support settlement | D6: Retain with settlement file; completed before approval | E6: COMPLETE | F6: Keep raw baselines and dimension-preserved marked layers together | G6: Final Lot Review Packet pp.1-2,4; Exception Markup DOCX image1-image4; Registry Lineage!A4:J9.
A7: Retain qualification-exception release audit | B7: Compliance Qualification Manager | C7: QX-38983-2025 exact LOT-D/unit case | D7: Before LOT-D settlement propagation; completed 11:36:20 EDT | E7: COMPLETE | F7: Preserve ordered REVIEW_HOLD → EVIDENCE_MATCHED → RELEASED events | G7: Qualification log rows 4,6,8; Qualification Exception!A4:J13.
A8: Prepare CY2024 annual Class I compliance filing | B8: Compliance | C8: Seller 950 + cover 40 with ownership support; residual 10 still open | D8: 2025-07-01 (date only; no time stated by authority) | E8: IN PROGRESS | F8: Use official workbook; keep unresolved certificates out of settled sub-account reporting until cured | G8: 225 CMR 14.00 p.34 §14.09(1)-(2)(c); Annual Compliance Workbook 5. RPS I non-SCO!F13 and 4. Errant!B9,B13; June Close Calendar p.1.

Sheet Evidence Index
A1: PUBLIC EVIDENCE INDEX
A2: Every public workspace file inspected. Visual business conclusions are based on rendered embedded pixels and reconciled with structured records.
A3: Public Source Path | B3: Exact Locator | C3: Observable Business Evidence | D3: Role / Authority Boundary | E3: Used In
A4: Accounting/Invoice Ledger.csv | B4: row 2; fields invoice_id through as_of | C4: INV-2025-0617 booked USD 18,000, UNAPPROVED, paid 0, prior credits 0 as of noon. | D4: Accounting control; booking is not delivery approval. | E4: Financial Bridge; Decision Summary
A5: Compliance/2024 Class I Inventory Control.xlsx | B5: Close Control!A2:E7 | C5: 1,000 close requirement, zero opening inventory, separate pending seller/cover/errant/residual inputs. | D5: Internal pre-settlement inventory schema. | E5: Inventory Posting
A6: Compliance/June Close Calendar.pdf | B6: p.1 | C6: Cure cutoff Jun 6 17:00; tender Jun 9 09:15; dispute Jun 16 17:00; filing Jul 1, separate clocks. | D6: Internal calendar corroborates contract/regulatory computations. | E6: Decision Summary; Action Register
A7: Compliance/Unit Qualification Exception Log QX-38983-2025.csv | B7: rows 4,6,8; fields case_id through owner | C7: Exact LOT-D/NON38983/1015-02/Deer Island case moves REVIEW_HOLD → EVIDENCE_MATCHED → RELEASED at 11:36:20 by manager. | D7: Internal close gate only; not program eligibility. | E7: Qualification Exception; Lot Dispositions
A8: Contracts/Amendment 1 - Cure and Cover.pdf | B8: p.1 §1; p.2 §2; p.3 §3; p.4 §§4-5; p.5 embedded signature image; p.6 embedded receipt reverse | C8: Expressly modifies cure/cover/damages; Jun 6 cutoff; independent substitute tests; positive differential; visual pair proves bilateral execution and receipt for AMD-REC-017-A1. | D8: Controlling commercial source within express scope after authentication. | E8: Contract Cure Controls; Financial Bridge
A9: Contracts/REC Purchase Confirmation REC-2024-017.pdf | B9: p.1 §§1-2; p.2 §§3-4; p.3 §§5-6; p.4 §§7-8 | C9: 2024 Class I product, 1,000 at USD 18, buyer account, acceptance, invoice/dispute, source precedence. | D9: Base commercial source except expressly amended cure/cover matters. | E9: All settlement schedules
A10: Correspondence/Prior Exception Notice EXC-24017.pdf | B10: p.1; p.2 embedded receipt image | C10: Case EXC-24017 questions LOT-B/LOT-C; visual receipt shows delivered Jun 3 16:18 EDT. | D10: Antecedent cure notice; makes no disposition. | E10: Contract Cure Controls
A11: Correspondence/Seller Cure Election EXC-24017.docx | B11: embedded word/media/image1.jpg; transmittal paras 1-3 | C11: Signed scan matches EXC-24017; Substitute Delivery is sole checked option; received Jun 6 16:41 EDT. | D11: Cure authorization, not automatic certificate acceptance. | E11: Contract Cure Controls; Lot Dispositions
A12: Delivery/Final Delivery Statement 2025-06-09.xlsx | B12: Tender Lots!A2:I7 | C12: All original/replacement lot identities, periods, inclusive ranges, stated quantities, final tender 09:15. | D12: Seller claim subject to authority, registry, and uniqueness tests. | E12: Lot Dispositions; Quantity Reconciliation
A13: Delivery/Invoice INV-2025-0617.pdf | B13: p.1 | C13: Bills 1,000 × USD 18 = USD 18,000; pending acceptance; AP booking is not approval. | D13: Seller invoice claim subject to reconciliation. | E13: Financial Bridge
A14: Procurement/Broker Confirmation BRK-88402.docx | B14: embedded word/media/image1.jpg | C14: Blotter row BRK-88402 / MAI24 / 40 / 22.50 / 10:47:26 / FILLED. | D14: Independent visual corroboration of executed cover economics. | E14: Contract Cure Controls; Financial Bridge
... A26: Settlement/Certificate Close Checklist.docx | B26: table 1 rows 2-9; para 4 | C26: Lists evidence owners, pending outcome controls, Jun 16 dispute and Jul 1 readiness actions. | D26: Pending checklist; no settlement answers. | E26: Action Register; Evidence Index
